issformat.py
issformat-0.0.3.data/scripts/issConverter.py
issformat-0.0.3.dist-info/DESCRIPTION.rst
issformat-0.0.3.dist-info/METADATA
issformat-0.0.3.dist-info/RECORD
issformat-0.0.3.dist-info/WHEEL
issformat-0.0.3.dist-info/metadata.json
issformat-0.0.3.dist-info/top_level.txt
