Metadata-Version: 2.0
Name: issformat
Version: 0.0.3
Summary: LOFAR international single station metadata interface
Home-page: https://github.com/griffinfoster/issformat
Author: Griffin Foster
Author-email: griffin.foster@gmail.com
License: GPL
Platform: *nix
Classifier: Development Status :: 4 - Beta
Classifier: Environment :: Console
Classifier: Natural Language :: English
Classifier: Operating System :: POSIX :: Linux
Classifier: Programming Language :: Python :: 2.7
Classifier: Intended Audience :: Science/Research
Classifier: License :: OSI Approved :: GNU General Public License (GPL)
Classifier: Topic :: Scientific/Engineering :: Astronomy
Requires: distutils
Requires: numpy
Requires: json
